README.md
setup.py
liqpay_async/__init__.py
liqpay_async/liq_pay.py
liqpay_async.egg-info/PKG-INFO
liqpay_async.egg-info/SOURCES.txt
liqpay_async.egg-info/dependency_links.txt
liqpay_async.egg-info/requires.txt
liqpay_async.egg-info/top_level.txt