Metadata-Version: 2.1
Name: liqpay-async
Version: 0.0.1
Summary: LiqPay Async Python3 SDK
Home-page: https://github.com/SpaceIgor/liqpay-async
